weetags/__init__.py
weetags/exceptions.py
weetags/loaders.py
weetags/tree.py
weetags/tree_builder.py
weetags/utils.py
weetags/engine/__init__.py
weetags/engine/engine.py
weetags/engine/schema.py
weetags/engine/sql.py
weetags-1.0.1.dist-info/LICENSE
weetags-1.0.1.dist-info/METADATA
weetags-1.0.1.dist-info/WHEEL
weetags-1.0.1.dist-info/top_level.txt
weetags-1.0.1.dist-info/RECORD
