Metadata-Version: 2.2
Name: weetags
Version: 1.0.1
Summary: Small and simple permanent tree database builded on top of Sqlite
Author-email: Romain Viry <rom88.viry@gmail.com>
Maintainer-email: Romain Viry <rom88.viry@gmail.com>
Project-URL: Source, https://github.com/morague/weetags
Keywords: Permanent Tree,database
Requires-Python: >=3.8
License-File: LICENSE
Requires-Dist: attrs>=23.2.0
Provides-Extra: test
Requires-Dist: pytest>=6.2.5; extra == "test"
Requires-Dist: pytest-cov>=3.0.0; extra == "test"
Provides-Extra: dev
Requires-Dist: commitizen>=2.27.1; extra == "dev"
Requires-Dist: yamllint>=1.35.1; extra == "dev"
Requires-Dist: ruff>=0.2.2; extra == "dev"
Requires-Dist: safety>=3.0.1; extra == "dev"
